{
  "annotations": {
    "list": [
      {
        "builtIn": 1,
        "datasource": {
          "type": "grafana",
          "uid": "-- Grafana --"
        },
        "enable": true,
        "hide": true,
        "iconColor": "rgba(0, 211, 255, 1)",
        "name": "Annotations & Alerts",
        "type": "dashboard"
      }
    ]
  },
  "editable": true,
  "fiscalYearStartMonth": 0,
  "graphTooltip": 1,
  "id": null,
  "links": [],
  "panels": [
    {
      "datasource": {
        "type": "prometheus",
        "uid": "${DS_PROMETHEUS}"
      },
      "fieldConfig": {
        "defaults": {
          "color": {
            "mode": "palette-classic"
          },
          "unit": "s"
        },
        "overrides": []
      },
      "gridPos": {
        "h": 8,
        "w": 12,
        "x": 0,
        "y": 0
      },
      "id": 1,
      "options": {
        "legend": {
          "calcs": [],
          "displayMode": "list",
          "placement": "bottom",
          "showLegend": true
        },
        "tooltip": {
          "mode": "single",
          "sort": "none"
        }
      },
      "targets": [
        {
          "editorMode": "code",
          "expr": "histogram_quantile(0.95, sum by (le, pod) (rate(vault_wal_flushready_bucket{namespace=\"$namespace\", pod=~\"$pod\"}[5m])))",
          "legendFormat": "{{pod}}",
          "refId": "A"
        }
      ],
      "title": "Replication: WAL Flush Ready p95",
      "type": "timeseries"
    },
    {
      "datasource": {
        "type": "prometheus",
        "uid": "${DS_PROMETHEUS}"
      },
      "fieldConfig": {
        "defaults": {
          "color": {
            "mode": "palette-classic"
          },
          "unit": "ops"
        },
        "overrides": []
      },
      "gridPos": {
        "h": 8,
        "w": 12,
        "x": 12,
        "y": 0
      },
      "id": 2,
      "options": {
        "legend": {
          "calcs": [],
          "displayMode": "list",
          "placement": "bottom",
          "showLegend": true
        },
        "tooltip": {
          "mode": "single",
          "sort": "none"
        }
      },
      "targets": [
        {
          "editorMode": "code",
          "expr": "sum by (pod) (rate(vault_wal_persistwals_total{namespace=\"$namespace\", pod=~\"$pod\"}[5m])) or sum by (pod) (rate(vault_wal_persistwals{namespace=\"$namespace\", pod=~\"$pod\"}[5m]))",
          "legendFormat": "{{pod}}",
          "refId": "A"
        }
      ],
      "title": "Replication/Storage: WAL Persist Rate",
      "type": "timeseries"
    },
    {
      "datasource": {
        "type": "prometheus",
        "uid": "${DS_PROMETHEUS}"
      },
      "fieldConfig": {
        "defaults": {
          "color": {
            "mode": "palette-classic"
          },
          "unit": "s"
        },
        "overrides": []
      },
      "gridPos": {
        "h": 8,
        "w": 12,
        "x": 0,
        "y": 8
      },
      "id": 3,
      "options": {
        "legend": {
          "calcs": [],
          "displayMode": "list",
          "placement": "bottom",
          "showLegend": true
        },
        "tooltip": {
          "mode": "single",
          "sort": "none"
        }
      },
      "targets": [
        {
          "editorMode": "code",
          "expr": "sum(rate(vault_audit_log_request_sum{namespace=\"$namespace\", pod=~\"$pod\"}[5m])) / clamp_min(sum(rate(vault_audit_log_request_count{namespace=\"$namespace\", pod=~\"$pod\"}[5m])), 1)",
          "legendFormat": "audit mean latency",
          "refId": "A"
        }
      ],
      "title": "Latency: Audit Log Request Mean (5m)",
      "type": "timeseries"
    },
    {
      "datasource": {
        "type": "prometheus",
        "uid": "${DS_PROMETHEUS}"
      },
      "fieldConfig": {
        "defaults": {
          "color": {
            "mode": "palette-classic"
          }
        },
        "overrides": [
          {
            "matcher": {
              "id": "byName",
              "options": "CPU (cores)"
            },
            "properties": [
              {
                "id": "unit",
                "value": "cores"
              }
            ]
          },
          {
            "matcher": {
              "id": "byName",
              "options": "Memory (bytes)"
            },
            "properties": [
              {
                "id": "unit",
                "value": "bytes"
              }
            ]
          },
          {
            "matcher": {
              "id": "byName",
              "options": "Request rate (rps)"
            },
            "properties": [
              {
                "id": "unit",
                "value": "reqps"
              }
            ]
          }
        ]
      },
      "gridPos": {
        "h": 8,
        "w": 12,
        "x": 12,
        "y": 8
      },
      "id": 4,
      "options": {
        "legend": {
          "calcs": [],
          "displayMode": "table",
          "placement": "bottom",
          "showLegend": true
        },
        "tooltip": {
          "mode": "multi",
          "sort": "none"
        }
      },
      "targets": [
        {
          "editorMode": "code",
          "expr": "sum(rate(container_cpu_usage_seconds_total{namespace=\"$namespace\", pod=~\"$pod\", container!=\"\", container!=\"POD\"}[5m]))",
          "legendFormat": "CPU (cores)",
          "refId": "A"
        },
        {
          "editorMode": "code",
          "expr": "sum(container_memory_working_set_bytes{namespace=\"$namespace\", pod=~\"$pod\", container!=\"\", container!=\"POD\"})",
          "legendFormat": "Memory (bytes)",
          "refId": "B"
        },
        {
          "editorMode": "code",
          "expr": "sum(rate(vault_core_handle_request_count{namespace=\"$namespace\", pod=~\"$pod\"}[5m]))",
          "legendFormat": "Request rate (rps)",
          "refId": "C"
        }
      ],
      "title": "Health/Resource: CPU, Memory, Request Count Rate",
      "type": "timeseries"
    },
    {
      "datasource": {
        "type": "prometheus",
        "uid": "${DS_PROMETHEUS}"
      },
      "fieldConfig": {
        "defaults": {
          "color": {
            "mode": "palette-classic"
          },
          "unit": "bytes"
        },
        "overrides": []
      },
      "gridPos": {
        "h": 8,
        "w": 24,
        "x": 0,
        "y": 16
      },
      "id": 5,
      "options": {
        "legend": {
          "calcs": [],
          "displayMode": "list",
          "placement": "bottom",
          "showLegend": true
        },
        "tooltip": {
          "mode": "single",
          "sort": "none"
        }
      },
      "targets": [
        {
          "editorMode": "code",
          "expr": "sum by (persistentvolumeclaim) (kubelet_volume_stats_used_bytes{namespace=\"$namespace\", persistentvolumeclaim=~\"data-vault-.*\"})",
          "legendFormat": "{{persistentvolumeclaim}}",
          "refId": "A"
        }
      ],
      "title": "Storage/WAL: Vault PVC Used Bytes",
      "type": "timeseries"
    }
  ],
  "refresh": "30s",
  "schemaVersion": 39,
  "tags": [
    "vault",
    "telemetry",
    "eks",
    "prometheus"
  ],
  "templating": {
    "list": [
      {
        "current": {},
        "name": "DS_PROMETHEUS",
        "query": "prometheus",
        "type": "datasource"
      },
      {
        "current": {
          "selected": true,
          "text": "vault",
          "value": "vault"
        },
        "datasource": {
          "type": "prometheus",
          "uid": "${DS_PROMETHEUS}"
        },
        "includeAll": false,
        "multi": false,
        "name": "namespace",
        "query": "label_values(up{namespace=~\"vault|monitoring\"}, namespace)",
        "refresh": 1,
        "type": "query"
      },
      {
        "allValue": ".*",
        "current": {
          "selected": true,
          "text": "All",
          "value": "$__all"
        },
        "datasource": {
          "type": "prometheus",
          "uid": "${DS_PROMETHEUS}"
        },
        "includeAll": true,
        "multi": true,
        "name": "pod",
        "query": "label_values(up{namespace=\"$namespace\"}, pod)",
        "refresh": 1,
        "type": "query"
      }
    ]
  },
  "time": {
    "from": "now-24h",
    "to": "now"
  },
  "timepicker": {},
  "timezone": "",
  "title": "Vault Telemetry - Replication, Latency, Health, Storage",
  "version": 1,
  "weekStart": ""
}
